arsa_pipeline_tools/__init__.py
arsa_pipeline_tools/utils.py
arsa_pipeline_tools-0.1.1.dist-info/LICENSE
arsa_pipeline_tools-0.1.1.dist-info/METADATA
arsa_pipeline_tools-0.1.1.dist-info/WHEEL
arsa_pipeline_tools-0.1.1.dist-info/top_level.txt
arsa_pipeline_tools-0.1.1.dist-info/RECORD
