Metadata-Version: 2.1
Name: arsa-pipeline-tools
Version: 0.1.1
Summary: Utilities for Vertex AI pipelines, including GCS file management and dynamic module loading.
Home-page: https://github.com/hrs19/arsa-pipeline-tools
Author: Harshit S
Author-email: hrs19.pypi@gmail.com
Classifier: Programming Language :: Python :: 3
Classifier: License :: OSI Approved :: MIT License
Classifier: Operating System :: OS Independent
Requires-Python: >=3.7
License-File: LICENSE
Requires-Dist: google-cloud-storage >=2.18.2
